sw_service_lib/__init__.py
sw_service_lib/billing.py
sw_service_lib/client.py
sw_service_lib/error.py
sw_service_lib/fast.py
sw_service_lib/job.py
sw_service_lib/platform.py
sw_service_lib/resource.py
sw_service_lib/service.py
sw_service_lib/transport.py
sw_service_lib-0.1.8.dist-info/WHEEL
sw_service_lib-0.1.8.dist-info/METADATA
sw_service_lib-0.1.8.dist-info/RECORD
